Workbook

Sheet Dashboard
A1: BETTING TEST ACCOUNT — ROLL-UP DASHBOARD
A2: Account rules: $5,000 total account · max $1,000 staked per card · max 4 cards active at any time. QUEUED cards hold no money and don't count against the cap. Settled cards archive after 7 days.
A4: ACCOUNT SUMMARY
A5: Starting Account | B5: 5000
A6: Net P/L to Date (all cards) | B6: =H25 -> -2056.3166
A7: Current Account Balance | B7: =B5+B6 -> 2943.6834
A8: At Risk (stakes on pending bets) | B8: =F25 -> 1000
A9: Available to Deploy | B9: =B7-B8 -> 1943.6834
A10: Active Cards | B10: =COUNTIF(D16:D24,"ACTIVE")&" of 4 max" -> 1 of 4 max
A11: Per-Card Stake Cap | B11: $1,000 (UFC card staked $1,050 — pre-dates rule; grandfathered)
A14: CARD TIMELINE — SORTED BY NEXT ACTION (settled at bottom)
A15: # | B15: Card / Event | C15: Event Date(s) | D15: Status | E15: Staked | F15: At Risk (pending) | G15: Returned to Date | H15: Net P/L to Date
A16: 9 | B16: WNBA Wednesday Slate | C16: 2026-07-15 | D16: SETTLED | E16: =SUM('WNBA Jul 15'!F7:F13) -> 1000 | F16: =SUMIF('WNBA Jul 15'!I7:I13,"Pending",'WNBA Jul 15'!F7:F13) -> 0 | G16: =SUM('WNBA Jul 15'!J7:J13) -> 553.14685 | H16: =SUM('WNBA Jul 15'!K7:K13) -> -446.85315
A17: 2 | B17: World Cup 2026 — Final Four | C17: Jul 14-19 | D17: SETTLED | E17: =SUM('World Cup 2026'!F7:F13) -> 1000 | F17: =SUMIF('World Cup 2026'!I7:I13,"Pending",'World Cup 2026'!F7:F13) -> 0 | G17: =SUM('World Cup 2026'!J7:J13) -> 630.86066 | H17: =SUM('World Cup 2026'!K7:K13) -> -369.13934
A18: 6 | B18: The Open Championship (golf) | C18: Jul 16-19 | D18: ACTIVE | E18: =SUM('The Open'!F7:F17) -> 1000 | F18: =SUMIF('The Open'!I7:I17,"Pending",'The Open'!F7:F17) -> 1000 | G18: =SUM('The Open'!J7:J17) -> 0 | H18: =SUM('The Open'!K7:K17) -> 0
A19: 7 | B19: Rugby Nations Cup — Final Rd | C19: 2026-07-18 | D19: QUEUED | E19: 0 | F19: 0 | G19: 0 | H19: 0
A20: 8 | B20: MLB Home Run Derby | C20: 2026-07-13 | D20: SETTLED | E20: =SUM('HR Derby'!F7:F13) -> 1000 | F20: =SUMIF('HR Derby'!I7:I13,"Pending",'HR Derby'!F7:F13) -> 0 | G20: =SUM('HR Derby'!J7:J13) -> 525 | H20: =SUM('HR Derby'!K7:K13) -> -475
A21: 4 | B21: NASCAR Quaker State 400 | C21: 2026-07-12 | D21: SETTLED | E21: =SUM('NASCAR Jul 12'!F7:F13) -> 1000 | F21: =SUMIF('NASCAR Jul 12'!I7:I13,"Pending",'NASCAR Jul 12'!F7:F13) -> 0 | G21: =SUM('NASCAR Jul 12'!J7:J13) -> 565.48673 | H21: =SUM('NASCAR Jul 12'!K7:K13) -> -434.51327
A22: 5 | B22: WNBA Sunday Doubleheader | C22: 2026-07-12 | D22: SETTLED | E22: =SUM('WNBA Jul 12'!F7:F13) -> 1000 | F22: =SUMIF('WNBA Jul 12'!I7:I13,"Pending",'WNBA Jul 12'!F7:F13) -> 0 | G22: =SUM('WNBA Jul 12'!J7:J13) -> 701.84651 | H22: =SUM('WNBA Jul 12'!K7:K13) -> -298.15349
A23: 3 | B23: MLB Sunday Slate (15 games) | C23: 2026-07-12 | D23: SETTLED | E23: =SUM('MLB Jul 12'!F7:F14) -> 1000 | F23: =SUMIF('MLB Jul 12'!I7:I14,"Pending",'MLB Jul 12'!F7:F14) -> 0 | G23: =SUM('MLB Jul 12'!J7:J14) -> 802.23226 | H23: =SUM('MLB Jul 12'!K7:K14) -> -197.76774
A24: 1 | B24: UFC 329: McGregor vs Holloway 2 | C24: 2026-07-11 | D24: SETTLED | E24: =SUM('UFC 329'!F7:F15) -> 1050 | F24: =SUMIF('UFC 329'!I7:I15,"Pending",'UFC 329'!F7:F15) -> 0 | G24: =SUM('UFC 329'!J7:J15) -> 1215.1104 | H24: =SUM('UFC 329'!K7:K15) -> 165.11037
B25: TOTALS | E25: =SUM(E16:E24) -> 8050 | F25: =SUM(F16:F24) -> 1000 | G25: =SUM(G16:G24) -> 4993.6834 | H25: =SUM(H16:H24) -> -2056.3166
A27: 🎲 LONGSHOT TRACKER — one per card, hit/miss record
A28: Card | B28: Longshot | C28: Odds | D28: Stake | E28: Status
A29: Test 1 · UFC 329 | B29: McGregor KO/TKO/Sub R1 | C29: +250 | D29: 0 | E29: MISS
A30: Test 3 · MLB Jul 12 | B30: 3-leg ML parlay (PIT+CIN+ATH) | C30: +732 | D30: 50 | E30: =IF('MLB Jul 12'!I14="Win","HIT",IF('MLB Jul 12'!I14="Loss","MISS","Pending")) -> MISS
A31: Test 4 · NASCAR Jul 12 | B31: Kyle Larson to win | C31: +1900 | D31: 40 | E31: =IF('NASCAR Jul 12'!I13="Win","HIT",IF('NASCAR Jul 12'!I13="Loss","MISS","Pending")) -> MISS
A32: Test 5 · WNBA Jul 12 | B32: 4-leg cross-game parlay | C32: +971 | D32: 100 | E32: =IF('WNBA Jul 12'!I13="Win","HIT",IF('WNBA Jul 12'!I13="Loss","MISS","Pending")) -> MISS
A33: Test 6 · The Open | B33: Brooks Koepka outright | C33: +5000 | D33: 50 | E33: =IF('The Open'!I12="Win","HIT",IF('The Open'!I12="Loss","MISS","Pending")) -> Pending
A34: Test 7 · Rugby Jul 18 | B34: TBD at finalization | C34: TBD | D34: 0 | E34: Queued
A35: Test 8 · HR Derby | B35: Willson Contreras outright | C35: +1400 | D35: 75 | E35: =IF('HR Derby'!I13="Win","HIT",IF('HR Derby'!I13="Loss","MISS","Pending")) -> MISS
A36: Test 9 · WNBA Jul 15 | B36: 4-leg cross-game parlay | C36: +1133 | D36: 75 | E36: =IF('WNBA Jul 15'!I13="Win","HIT",IF('WNBA Jul 15'!I13="Loss","MISS","Pending")) -> MISS
A37: LONGSHOT HIT RATE | E37: =IF(COUNTIF(E29:E36,"HIT")+COUNTIF(E29:E36,"MISS")=0,"—",COUNTIF(E29:E36,"HIT")&"-for-"&(COUNTIF(E29:E36,"HIT")+COUNTIF(E29:E36,"MISS"))&" ("&TEXT(COUNTIF(E29:E36,"HIT")/(COUNTIF(E29:E36,"HIT")+COUNTIF(E29:E36,"MISS")),"0%")&")") -> 0-for-6 (0%)
A38: Note: WC card carries an England hedge, not a longshot — excluded. UFC longshot was $0-stake and missed.

Sheet UFC 329
A1: TEST 1 — UFC 329: McGREGOR vs HOLLOWAY 2 | H1: STATUS: ARCHIVED — settled Jul 11, 2026 (drops off dashboard Jul 18)
A2: T-Mobile Arena, Las Vegas · July 11, 2026 · Source: ufc329-betting-card.html (odds: DraftKings/BetMGM/CBS as of Jul 11, 2026)
A3: Budget $1,000 deployed on 8 straight bets + $50 bonus parlay = $1,050 total exposure (parlay was flagged as a bonus play on the card).
A5: ACTIVE BETS
A6: # | B6: Pick | C6: Fight / Market | D6: Bet Type | E6: Odds (Am.) | F6: Stake | G6: To Win | H6: Potential Return | I6: Result | J6: Returned | K6: P/L | L6: Notes
A7: 1 | B7: Max Holloway ML | C7: vs Conor McGregor · WW Main Event | D7: Moneyline | E7: -265 | F7: 265 | G7: =IF(E7>0,F7*E7/100,F7*100/ABS(E7)) -> 100 | H7: =F7+G7 -> 365 | I7: Win | J7: =IF(I7="Win",F7+G7,IF(I7="Push",F7,IF(I7="Loss",0,0))) -> 365 | K7: =IF(I7="Pending",0,J7-F7) -> 100 | L7: Anchor play — 78% confidence on card · RESULT: Holloway TKO (McGregor knee injury) R1 1:09
A8: 2 | B8: Holloway by KO/TKO | C8: vs McGregor · Method of victory | D8: Prop | E8: -140 | F8: 200 | G8: =IF(E8>0,F8*E8/100,F8*100/ABS(E8)) -> 142.85714 | H8: =F8+G8 -> 342.85714 | I8: Win | J8: =IF(I8="Win",F8+G8,IF(I8="Push",F8,IF(I8="Loss",0,0))) -> 342.85714 | K8: =IF(I8="Pending",0,J8-F8) -> 142.85714 | L8: Card's 'best value' — predicted R3 stoppage · RESULT: Official method TKO — graded Win (injury stoppage; see note)
A9: 3 | B9: Benoît Saint-Denis ML | C9: vs Paddy Pimblett · LW Co-Main | D9: Moneyline | E9: -148 | F9: 148 | G9: =IF(E9>0,F9*E9/100,F9*100/ABS(E9)) -> 100 | H9: =F9+G9 -> 248 | I9: Loss | J9: =IF(I9="Win",F9+G9,IF(I9="Push",F9,IF(I9="Loss",0,0))) -> 0 | K9: =IF(I9="Pending",0,J9-F9) -> -148 | L9: 4 straight stoppage wins · RESULT: Pimblett subbed BSD (D'Arce) R1 0:52
A10: 4 | B10: Mario Bautista ML | C10: vs Cory Sandhagen · BW | D10: Moneyline | E10: 114 | F10: 100 | G10: =IF(E10>0,F10*E10/100,F10*100/ABS(E10)) -> 114 | H10: =F10+G10 -> 214 | I10: Win | J10: =IF(I10="Win",F10+G10,IF(I10="Push",F10,IF(I10="Loss",0,0))) -> 214 | K10: =IF(I10="Pending",0,J10-F10) -> 114 | L10: 10-1 in last 11, underdog value · RESULT: Bautista UD 29-28 x3
A11: 5 | B11: Lone'er Kavanagh ML | C11: vs Brandon Royval · FLW | D11: Moneyline | E11: -218 | F11: 100 | G11: =IF(E11>0,F11*E11/100,F11*100/ABS(E11)) -> 45.87156 | H11: =F11+G11 -> 145.87156 | I11: Loss | J11: =IF(I11="Win",F11+G11,IF(I11="Push",F11,IF(I11="Loss",0,0))) -> 0 | K11: =IF(I11="Pending",0,J11-F11) -> -100 | L11: Dominated Moreno; market agrees · RESULT: Royval subbed Kavanagh (RNC) R3 3:39
A12: 6 | B12: Robert Whittaker ML | C12: vs Nikita Krylov · LHW (prelim) | D12: Moneyline | E12: -125 | F12: 75 | G12: =IF(E12>0,F12*E12/100,F12*100/ABS(E12)) -> 60 | H12: =F12+G12 -> 135 | I12: Win | J12: =IF(I12="Win",F12+G12,IF(I12="Push",F12,IF(I12="Loss",0,0))) -> 135 | K12: =IF(I12="Pending",0,J12-F12) -> 60 | L12: Slight edge at near-even price · RESULT: Whittaker KO (punch) R3 1:01
A13: 7 | B13: Luke Riley ML | C13: vs Kamaka III · FW (prelim) | D13: Moneyline | E13: -225 | F13: 50 | G13: =IF(E13>0,F13*E13/100,F13*100/ABS(E13)) -> 22.222222 | H13: =F13+G13 -> 72.222222 | I13: Win | J13: =IF(I13="Win",F13+G13,IF(I13="Push",F13,IF(I13="Loss",0,0))) -> 72.222222 | K13: =IF(I13="Pending",0,J13-F13) -> 22.222222 | L13: Unbeaten prospect · RESULT: Riley TKO R1 3:03
A14: 8 | B14: Damian Pinas ML | C14: vs Cesar Almeida · MW (early prelim) | D14: Moneyline | E14: -258 | F14: 62 | G14: =IF(E14>0,F14*E14/100,F14*100/ABS(E14)) -> 24.031008 | H14: =F14+G14 -> 86.031008 | I14: Win | J14: =IF(I14="Win",F14+G14,IF(I14="Push",F14,IF(I14="Loss",0,0))) -> 86.031008 | K14: =IF(I14="Pending",0,J14-F14) -> 24.031008 | L14: 5-fight KO streak, 5.5" reach edge · RESULT: Pinas KO (punch) R1 4:44
A15: 9 | B15: 3-Leg Parlay | C15: Holloway KO/TKO + Saint-Denis ML + Bautista ML | D15: Parlay | E15: 443 | F15: 50 | G15: =IF(E15>0,F15*E15/100,F15*100/ABS(E15)) -> 221.5 | H15: =F15+G15 -> 271.5 | I15: Loss | J15: =IF(I15="Win",F15+G15,IF(I15="Push",F15,IF(I15="Loss",0,0))) -> 0 | K15: =IF(I15="Pending",0,J15-F15) -> -50 | L15: Bonus play — combined ≈ +443 · RESULT: Parlay dead — Saint-Denis leg lost (other 2 legs won)
B16: TOTALS | F16: =SUM(F7:F15) -> 1050 | G16: =SUM(G7:G15) -> 830.48193 | H16: =SUM(H7:H15) -> 1880.4819 | J16: =SUM(J7:J15) -> 1215.1104 | K16: =SUM(K7:K15) -> 165.11037
B18: SCORECARD
B19: Wins | C19: =COUNTIF(I7:I15,"Win") -> 6
B20: Losses | C20: =COUNTIF(I7:I15,"Loss") -> 3
B21: Pushes | C21: =COUNTIF(I7:I15,"Push") -> 0
B22: Pending | C22: =COUNTIF(I7:I15,"Pending") -> 0
B23: Hit Rate | C23: =IF(COUNTIF(I7:I15,"Win")+COUNTIF(I7:I15,"Loss")=0,"—",COUNTIF(I7:I15,"Win")/(COUNTIF(I7:I15,"Win")+COUNTIF(I7:I15,"Loss"))) -> 0.66666667
B24: Total Staked | C24: =SUM(F7:F15) -> 1050
B25: Total Returned | C25: =SUM(J7:J15) -> 1215.1104
B26: Net P/L | C26: =SUM(K7:K15) -> 165.11037
B27: ROI | C27: =IF(SUM(F7:F15)=0,"—",SUM(K7:K15)/SUM(F7:F15)) -> 0.15724797
B28: Max Return (all hit) | C28: =SUM(H7:H15) -> 1880.4819
A30: SKIPPED FIGHTS & $0 PLAYS (tracked to grade the skip decisions — no money at stake)
A31: # | B31: Fight | C31: Card Note | D31: Listed Odds | E31: Winner (fill in) | F31: Skip Verdict (fill in)
A32: 1 | B32: Terrance McKinney vs King Green | C32: Skip — coin flip, line too short for juice | D32: -115 | E32: King Green (TKO R1) | F32: GOOD SKIP — McKinney side lost
A33: 2 | B33: Gable Steveson vs Ellison | C33: Skip — -1450 juice, no payout worth risk | D33: -1450 | E33: Steveson (TKO R1) | F33: Good skip — won but -1450 payout tiny
A34: 3 | B34: Adrian Yanez vs Cody Garbrandt | C34: Skip — -425 too juiced; Garbrandt KO risk | D34: -425 | E34: Yanez (TKO R1) | F34: Fair skip — won, but -425 risk was real
A35: 4 | B35: Farid Basharat vs Garza | C35: Skip — -675 unplayable juice | D35: -675 | E35: Basharat (UD) | F35: Fair skip — won at -675, tiny payout
A36: 5 | B36: Wang Cong vs Tracy Cortez | C36: Skip — true pick'em | D36: -118 | E36: Wang Cong (UD) | F36: Neutral — true pick'em, no lean
A37: 6 | B37: McGregor KO/TKO/Sub R1 (longshot) | C37: $0 stake — flagged as fun play only at +250 | D37: +250 | E37: Did not hit — McGregor lost R1 | F37: GOOD $0 — would have lost stake
A39: Yellow cells = fill in results here (Result column: Win / Loss / Push / Pending via dropdown). Blue = inputs. Black = formulas — don't overwrite.
A40: Note: the HTML card's "$2,741 if all hit" figure overstates the true max return — the formulas here compute the correct number from odds and stakes.
A41: Grading note: Holloway 'by KO/TKO' graded WIN — official result was TKO (R1 1:09, McGregor knee injury on jumping kick). Standard book grading follows the official method (TKO), though a few books void injury stoppages; we use official-result grading for this test.

Sheet World Cup 2026
A1: TEST 2 — FIFA WORLD CUP 2026: THE FINAL FOUR | H1: STATUS: SETTLED — 2-5, -$369.14 · Both semifinal sides advance against us; final is Spain-Argentina
A2: Semifinals Jul 14-15 · Final Jul 19 (MetLife) · Source: wc2026-betting-card.html · Odds: BetMGM outrights Jul 11, FanDuel/DK semifinal openers Jul 11-12
A3: Budget $1,000 fully deployed on 7 bets. NOTE: portfolio is hedged — Arg ML vs Draw, and France vs England outrights are mutually exclusive; best case = 5 of 7 cash (+$929).
A5: ACTIVE BETS
A6: # | B6: Pick | C6: Match / Market | D6: Bet Type | E6: Odds (Am.) | F6: Stake | G6: To Win | H6: Potential Return | I6: Result | J6: Returned | K6: P/L | L6: Notes
A7: 1 | B7: France to Advance to Final | C7: vs Spain · SF1 · Tue Jul 14 (incl. ET/pens) | D7: To Advance | E7: -144 | F7: 300 | G7: =IF(E7>0,F7*E7/100,F7*100/ABS(E7)) -> 208.33333 | H7: =F7+G7 -> 508.33333 | I7: Loss | J7: =IF(I7="Win",F7+G7,IF(I7="Push",F7,IF(I7="Loss",0,0))) -> 0 | K7: =IF(I7="Pending",0,J7-F7) -> -300 | L7: Anchor — 62% confidence, most complete squad left · RESULT: Spain 2-0 France — France out, ticket dead
A8: 2 | B8: France vs Spain Under 2.5 (90') | C8: SF1 total goals | D8: Total | E8: -122 | F8: 120 | G8: =IF(E8>0,F8*E8/100,F8*100/ABS(E8)) -> 98.360656 | H8: =F8+G8 -> 218.36066 | I8: Win | J8: =IF(I8="Win",F8+G8,IF(I8="Push",F8,IF(I8="Loss",0,0))) -> 218.36066 | K8: =IF(I8="Pending",0,J8-F8) -> 98.360656 | L8: Spain 1 GA all tournament; France 0 GA in knockouts · RESULT: 2 goals in the match — under 2.5 cashes
A9: 3 | B9: Argentina ML (90 min) | C9: vs England · SF2 · Wed Jul 15, Atlanta | D9: 3-Way ML | E9: 175 | F9: 150 | G9: =IF(E9>0,F9*E9/100,F9*100/ABS(E9)) -> 262.5 | H9: =F9+G9 -> 412.5 | I9: Win | J9: =IF(I9="Win",F9+G9,IF(I9="Push",F9,IF(I9="Loss",0,0))) -> 412.5 | K9: =IF(I9="Pending",0,J9-F9) -> 262.5 | L9: Messi scored in every game (8); England needed AET in QF · RESULT: Argentina 2-1 in 90 (Fernandez 85, Lautaro 90+2 after Gordon 55) — ML cashes
A10: 4 | B10: Argentina vs England Draw (90') | C10: SF2 · pairs with Arg ML | D10: 3-Way ML | E10: 205 | F10: 80 | G10: =IF(E10>0,F10*E10/100,F10*100/ABS(E10)) -> 164 | H10: =F10+G10 -> 244 | I10: Loss | J10: =IF(I10="Win",F10+G10,IF(I10="Push",F10,IF(I10="Loss",0,0))) -> 0 | K10: =IF(I10="Pending",0,J10-F10) -> -80 | L10: Structured: only England 90' win beats both tickets · RESULT: decided in regulation, no draw — ticket dead
A11: 5 | B11: France to Win World Cup | C11: Outright · Final Jul 19 | D11: Outright | E11: 160 | F11: 250 | G11: =IF(E11>0,F11*E11/100,F11*100/ABS(E11)) -> 400 | H11: =F11+G11 -> 650 | I11: Loss | J11: =IF(I11="Win",F11+G11,IF(I11="Push",F11,IF(I11="Loss",0,0))) -> 0 | K11: =IF(I11="Pending",0,J11-F11) -> -250 | L11: Book 38.5% implied vs Kalshi 40.7% — value on the favorite · RESULT: France eliminated in semis by Spain — outright dead
A12: 6 | B12: England to Win World Cup | C12: Outright · hedge ticket | D12: Outright | E12: 500 | F12: 50 | G12: =IF(E12>0,F12*E12/100,F12*100/ABS(E12)) -> 250 | H12: =F12+G12 -> 300 | I12: Loss | J12: =IF(I12="Win",F12+G12,IF(I12="Push",F12,IF(I12="Loss",0,0))) -> 0 | K12: =IF(I12="Pending",0,J12-F12) -> -50 | L12: Pays if the coin-flip semi goes against our Argentina lean · RESULT: England eliminated in semis by Argentina — outright dead
A13: 7 | B13: 2-Leg Parlay | C13: France to Advance (-144) + Arg/Eng U2.5 (-155) | D13: Parlay | E13: 179 | F13: 50 | G13: =IF(E13>0,F13*E13/100,F13*100/ABS(E13)) -> 89.5 | H13: =F13+G13 -> 139.5 | I13: Loss | J13: =IF(I13="Win",F13+G13,IF(I13="Push",F13,IF(I13="Loss",0,0))) -> 0 | K13: =IF(I13="Pending",0,J13-F13) -> -50 | L13: Chalk + under · combined ≈ +179 · RESULT: France to Advance leg dead (and Arg-Eng went over 2.5) — parlay dead
B14: TOTALS | F14: =SUM(F7:F13) -> 1000 | G14: =SUM(G7:G13) -> 1472.694 | H14: =SUM(H7:H13) -> 2472.694 | J14: =SUM(J7:J13) -> 630.86066 | K14: =SUM(K7:K13) -> -369.13934
B16: SCORECARD
B17: Wins | C17: =COUNTIF(I7:I13,"Win") -> 2
B18: Losses | C18: =COUNTIF(I7:I13,"Loss") -> 5
B19: Pushes | C19: =COUNTIF(I7:I13,"Push") -> 0
B20: Pending | C20: =COUNTIF(I7:I13,"Pending") -> 0
B21: Hit Rate | C21: =IF(COUNTIF(I7:I13,"Win")+COUNTIF(I7:I13,"Loss")=0,"—",COUNTIF(I7:I13,"Win")/(COUNTIF(I7:I13,"Win")+COUNTIF(I7:I13,"Loss"))) -> 0.28571429
B22: Total Staked | C22: =SUM(F7:F13) -> 1000
B23: Total Returned | C23: =SUM(J7:J13) -> 630.86066
B24: Net P/L | C24: =SUM(K7:K13) -> -369.13934
B25: ROI | C25: =IF(SUM(F7:F13)=0,"—",SUM(K7:K13)/SUM(F7:F13)) -> -0.36913934
B26: Best-Case P/L (hedged book) | C26: =929 -> 929
A28: SKIPPED MARKETS (tracked to grade skip decisions — no money at stake)
A29: # | B29: Market | C29: Card Note | D29: Listed Odds | E29: Outcome (fill in) | F29: Skip Verdict (fill in)
A30: 1 | B30: Spain to Win World Cup | C30: Skip — book implies 25% vs Kalshi 17%; worst price on board | D30: +300
A31: 2 | B31: Argentina to Win World Cup | C31: Skip — fair price but doubles Arg ML exposure | D31: +400
A32: 3 | B32: England ML 90' (vs Argentina) | C32: Skip — took the Arg/Draw structure instead | D32: +180
A33: 4 | B33: France ML 90' (vs Spain) | C33: Skip — to-advance line covers the ET/pens path | D33: +130
A35: Yellow cells = fill in results (Result dropdown: Win/Loss/Push/Pending). Blue = inputs. Black = formulas. Parlay 'to win' uses +179 (exact combined -144 × -155 = +178.8; ~$0.12 rounding).

Sheet MLB Jul 12
A1: TEST 3 — MLB SUNDAY SLATE · JULY 12, 2026 | H1: STATUS: ARCHIVED — settled Jul 12 (3-5, -$197.77)
A2: 15-game slate, 8 bets · Source: mlb-jul12-betting-card.html · Lines: ESPN consensus board, Sunday AM · Research: VSiN, PickDawgz, DK Network
A3: Budget $1,000 fully deployed. Est. Win % = our model; card expected value ≈ +$45 (~3.9 of 8 expected to cash).
A5: ACTIVE BETS
A6: # | B6: Pick | C6: Game / Market | D6: Bet Type | E6: Odds (Am.) | F6: Stake | G6: To Win | H6: Potential Return | I6: Result | J6: Returned | K6: P/L | L6: Est. Win % | M6: Notes
A7: 1 | B7: Giants ML | C7: vs Rockies · McDonald vs Lorenzen (6.46 ERA) | D7: Moneyline | E7: -155 | F7: 200 | G7: =IF(E7>0,F7*E7/100,F7*100/ABS(E7)) -> 129.03226 | H7: =F7+G7 -> 329.03226 | I7: Win | J7: =IF(I7="Win",F7+G7,IF(I7="Push",F7,IF(I7="Loss",0,0))) -> 329.03226 | K7: =IF(I7="Pending",0,J7-F7) -> 129.03226 | L7: 0.62 | M7: Safest play — Lorenzen 1.4 HR/9, Rockies worst road team · RESULT: SF 3-1 · Lorenzen fade lands
A8: 2 | B8: Athletics ML | C8: @ White Sox · Ginn (2.49 road ERA) vs Schultz (5.4 BB/9) | D8: Moneyline | E8: -104 | F8: 150 | G8: =IF(E8>0,F8*E8/100,F8*100/ABS(E8)) -> 144.23077 | H8: =F8+G8 -> 294.23077 | I8: Loss | J8: =IF(I8="Win",F8+G8,IF(I8="Push",F8,IF(I8="Loss",0,0))) -> 0 | K8: =IF(I8="Pending",0,J8-F8) -> -150 | L8: 0.54 | M8: Clearest starter mismatch priced near even · RESULT: CWS 9-1 · Ginn 8 ER in 4.1, six-run 1st
A9: 3 | B9: Tigers ML | C9: vs Phillies · Skubal vs Wheeler ace duel | D9: Moneyline | E9: -115 | F9: 150 | G9: =IF(E9>0,F9*E9/100,F9*100/ABS(E9)) -> 130.43478 | H9: =F9+G9 -> 280.43478 | I9: Loss | J9: =IF(I9="Win",F9+G9,IF(I9="Push",F9,IF(I9="Loss",0,0))) -> 0 | K9: =IF(I9="Pending",0,J9-F9) -> -150 | L9: 0.55 | M9: Bullpen edge: DET 3.10 ERA (3rd) vs PHI 5.41 (26th) since Jun 1 · RESULT: PHI 5-0 · Wheeler 10 K shutout; pen edge moot
A10: 4 | B10: Royals @ Orioles Under 9.5 | C10: Totals · Lugo vs Baz | D10: Total | E10: -114 | F10: 120 | G10: =IF(E10>0,F10*E10/100,F10*100/ABS(E10)) -> 105.26316 | H10: =F10+G10 -> 225.26316 | I10: Loss | J10: =IF(I10="Win",F10+G10,IF(I10="Push",F10,IF(I10="Loss",0,0))) -> 0 | K10: =IF(I10="Pending",0,J10-F10) -> -120 | L10: 0.55 | M10: KC last in road scoring 3.8 R/G; Baz 3.78 FIP · RESULT: BAL 8-2 · 10 combined runs, over by half a run
A11: 5 | B11: Pirates ML | C11: vs Brewers · Skenes (2.98 FIP) at home | D11: Moneyline | E11: 104 | F11: 130 | G11: =IF(E11>0,F11*E11/100,F11*100/ABS(E11)) -> 135.2 | H11: =F11+G11 -> 265.2 | I11: Win | J11: =IF(I11="Win",F11+G11,IF(I11="Push",F11,IF(I11="Loss",0,0))) -> 265.2 | K11: =IF(I11="Pending",0,J11-F11) -> 135.2 | L11: 0.52 | M11: Plus money on slate's best pitcher; PIT swept Sat DH; Gasser 4.98 FIP · RESULT: PIT 14-5 F, Skenes W (5.1 IP, 7 K), Gasser 7 ER
A12: 6 | B12: Reds ML | C12: vs Cubs · Abbott ≤3 ER in 14 straight starts | D12: Moneyline | E12: 108 | F12: 100 | G12: =IF(E12>0,F12*E12/100,F12*100/ABS(E12)) -> 108 | H12: =F12+G12 -> 208 | I12: Loss | J12: =IF(I12="Win",F12+G12,IF(I12="Push",F12,IF(I12="Loss",0,0))) -> 0 | K12: =IF(I12="Pending",0,J12-F12) -> -100 | L12: 0.5 | M12: Home dog with the more reliable starter · RESULT: CHC 8-4 · home-dog value didn't land
A13: 7 | B13: Mariners ML | C13: @ Rays · Hancock 3.23 vs Seymour 4.11 | D13: Moneyline | E13: 108 | F13: 100 | G13: =IF(E13>0,F13*E13/100,F13*100/ABS(E13)) -> 108 | H13: =F13+G13 -> 208 | I13: Win | J13: =IF(I13="Win",F13+G13,IF(I13="Push",F13,IF(I13="Loss",0,0))) -> 208 | K13: =IF(I13="Pending",0,J13-F13) -> 108 | L13: 0.5 | M13: Seymour's 6-1 record masks a 4.11 ERA · RESULT: SEA 8-2 · Crawford 3 RBI; pen covered Hancock's exit
A14: 8 | B14: Longshot: 3-Leg ML Parlay | C14: Pirates ML +104 / Reds ML +108 / Athletics ML -104 | D14: Parlay | E14: 732 | F14: 50 | G14: =IF(E14>0,F14*E14/100,F14*100/ABS(E14)) -> 366 | H14: =F14+G14 -> 416 | I14: Loss | J14: =IF(I14="Win",F14+G14,IF(I14="Push",F14,IF(I14="Loss",0,0))) -> 0 | K14: =IF(I14="Pending",0,J14-F14) -> -50 | L14: 0.14 | M14: The mandatory longshot — stacks our three value legs · RESULT: Parlay dead — Reds & A's legs lost (PIT leg won)
B15: TOTALS | F15: =SUM(F7:F14) -> 1000 | G15: =SUM(G7:G14) -> 1226.161 | H15: =SUM(H7:H14) -> 2226.161 | J15: =SUM(J7:J14) -> 802.23226 | K15: =SUM(K7:K14) -> -197.76774 | L15: =SUM(L7:L14) -> 3.92
B17: SCORECARD
B18: Wins | C18: =COUNTIF(I7:I14,"Win") -> 3
B19: Losses | C19: =COUNTIF(I7:I14,"Loss") -> 5
B20: Pushes | C20: =COUNTIF(I7:I14,"Push") -> 0
B21: Pending | C21: =COUNTIF(I7:I14,"Pending") -> 0
B22: Hit Rate | C22: =IF(COUNTIF(I7:I14,"Win")+COUNTIF(I7:I14,"Loss")=0,"—",COUNTIF(I7:I14,"Win")/(COUNTIF(I7:I14,"Win")+COUNTIF(I7:I14,"Loss"))) -> 0.375
B23: Total Staked | C23: =SUM(F7:F14) -> 1000
B24: Total Returned | C24: =SUM(J7:J14) -> 802.23226
B25: Net P/L | C25: =SUM(K7:K14) -> -197.76774
B26: ROI | C26: =IF(SUM(F7:F14)=0,"—",SUM(K7:K14)/SUM(F7:F14)) -> -0.19776774
B27: Max Return (all hit) | C27: =SUM(H7:H14) -> 2226.161
B28: Expected Wins (model) | C28: =SUM(L7:L14) -> 3.92
B29: Expected Value (model) | C29: =SUMPRODUCT(L7:L14,G7:G14)-SUMPRODUCT(1-L7:L14,F7:F14) -> 45.162483
A31: SKIPPED GAMES (tracked to grade skip decisions — no money at stake)
A32: # | B32: Game | C32: Card Note | D32: Listed Line | E32: Winner (fill in) | F32: Skip Verdict (fill in)
A33: 1 | B33: Yankees @ Nationals | C33: Skip — near coin flip, no starter edge | D33: NYY -114
A34: 2 | B34: Red Sox @ Mets | C34: Skip — Tolle good but line already fair | D34: BOS -126
A35: 3 | B35: Guardians @ Marlins | C35: Skip — no edge either way | D35: MIA -115
A36: 4 | B36: Angels @ Twins | C36: Skip — no edge | D36: MIN -136
A37: 5 | B37: Braves @ Cardinals | C37: Skip — two 4.5+ ERA starters, unpredictable | D37: STL -136
A38: 6 | B38: Astros @ Rangers | C38: Skip — Javier 10.22 ERA returning, unquantifiable | D38: TEX -131
A39: 7 | B39: D-backs @ Dodgers | C39: Skip — LAD -219 too juiced; ARI +178 tempting but pass | D39: LAD -219
A40: 8 | B40: Blue Jays @ Padres | C40: Skip — Gausman 4-8, no edge | D40: TOR -126
A42: Yellow = fill in results (dropdown: Win/Loss/Push/Pending). Blue = inputs. Black = formulas. Parlay odds +732 = (+104 × +108 × -104) compounded; grades as one bet.

Sheet NASCAR Jul 12
A1: TEST 4 — NASCAR QUAKER STATE 400 · ECHOPARK SPEEDWAY (ATLANTA) · JULY 12, 2026 | H1: STATUS: SETTLED — Blaney won in OT ~12:55 AM CT Mon after 3h lightning red flag · card 1-6, net -$434.51
A2: Race ~7:00 PM ET on TNT · Source: nascar-jul12-betting-card.html · Odds: Covers/VSiN/CBS (FanDuel) consensus, Sunday PM
A3: HIGH-VARIANCE TEST: drafting track, 38 DNFs in last 4 races. Bets 3-7 are a mutually exclusive winner basket — at most one can cash. Expected hits ~1.2 of 7 by design.
A5: ACTIVE BETS
A6: # | B6: Pick | C6: Market | D6: Bet Type | E6: Odds (Am.) | F6: Stake | G6: To Win | H6: Potential Return | I6: Result | J6: Returned | K6: P/L | L6: Est. Win % | M6: Notes
A7: 1 | B7: Blaney beats Byron (H2H) | C7: Head-to-head finishing matchup | D7: Matchup | E7: -113 | F7: 300 | G7: =IF(E7>0,F7*E7/100,F7*100/ABS(E7)) -> 265.48673 | H7: =F7+G7 -> 565.48673 | I7: Win | J7: =IF(I7="Win",F7+G7,IF(I7="Push",F7,IF(I7="Loss",0,0))) -> 565.48673 | K7: =IF(I7="Pending",0,J7-F7) -> 265.48673 | L7: 0.58 | M7: 7 top-10s in last 8 here; 1 wreck in 16 starts vs Byron's 4 in 14 · WIN — Blaney won the race outright (OT, ~12:55 AM CT Mon); H2H over Byron clinched
A8: 2 | B8: Daniel Suarez Top-5 | C8: Finishing position prop | D8: Prop | E8: 456 | F8: 200 | G8: =IF(E8>0,F8*E8/100,F8*100/ABS(E8)) -> 912 | H8: =F8+G8 -> 1112 | I8: Loss | J8: =IF(I8="Win",F8+G8,IF(I8="Push",F8,IF(I8="Loss",0,0))) -> 0 | K8: =IF(I8="Pending",0,J8-F8) -> -200 | L8: 0.24 | M8: Top-5 in 4 of last 6 Atlanta races; biggest % edge on card · LOSS — official top 5: Blaney, Bell, Hocevar, Gibbs, E. Jones; Suárez outside top 5
A9: 3 | B9: Chase Elliott to Win | C9: Outright winner | D9: Outright | E9: 1150 | F9: 150 | G9: =IF(E9>0,F9*E9/100,F9*100/ABS(E9)) -> 1725 | H9: =F9+G9 -> 1875 | I9: Loss | J9: =IF(I9="Win",F9+G9,IF(I9="Push",F9,IF(I9="Loss",0,0))) -> 0 | K9: =IF(I9="Pending",0,J9-F9) -> -150 | L9: 0.1 | M9: Defending race winner, Georgia native, Chevy won 4 of last 5 here · LOSS — Elliott did not win (Blaney P1)
A10: 4 | B10: Carson Hocevar to Win | C10: Outright winner | D10: Outright | E10: 1567 | F10: 120 | G10: =IF(E10>0,F10*E10/100,F10*100/ABS(E10)) -> 1880.4 | H10: =F10+G10 -> 2000.4 | I10: Loss | J10: =IF(I10="Win",F10+G10,IF(I10="Push",F10,IF(I10="Loss",0,0))) -> 0 | K10: =IF(I10="Pending",0,J10-F10) -> -120 | L10: 0.08 | M10: 3 straight Atlanta top-10s; elite drafter · LOSS — Hocevar P3; closest of the winner basket
A11: 5 | B11: Brad Keselowski to Win | C11: Outright winner | D11: Outright | E11: 1800 | F11: 100 | G11: =IF(E11>0,F11*E11/100,F11*100/ABS(E11)) -> 1800 | H11: =F11+G11 -> 1900 | I11: Loss | J11: =IF(I11="Win",F11+G11,IF(I11="Push",F11,IF(I11="Loss",0,0))) -> 0 | K11: =IF(I11="Pending",0,J11-F11) -> -100 | L11: 0.07 | M11: 2 Atlanta wins, 6 top-3s; CBS model top pick; RFK form · LOSS — Keselowski did not win
A12: 6 | B12: Tyler Reddick to Win | C12: Outright winner | D12: Outright | E12: 1150 | F12: 90 | G12: =IF(E12>0,F12*E12/100,F12*100/ABS(E12)) -> 1035 | H12: =F12+G12 -> 1125 | I12: Loss | J12: =IF(I12="Win",F12+G12,IF(I12="Push",F12,IF(I12="Loss",0,0))) -> 0 | K12: =IF(I12="Pending",0,J12-F12) -> -90 | L12: 0.08 | M12: Drafting ace; Toyota gambled on race trim over qualifying · LOSS — Reddick did not win (P8 per post-race reports)
A13: 7 | B13: Kyle Larson to Win (LONGSHOT) | C13: Outright winner | D13: Outright | E13: 1900 | F13: 40 | G13: =IF(E13>0,F13*E13/100,F13*100/ABS(E13)) -> 760 | H13: =F13+G13 -> 800 | I13: Loss | J13: =IF(I13="Win",F13+G13,IF(I13="Push",F13,IF(I13="Loss",0,0))) -> 0 | K13: =IF(I13="Pending",0,J13-F13) -> -40 | L13: 0.05 | M13: Mandatory longshot — best driver at his longest price; P3 start · LOSS — Larson did not win; longshot record now 0-for-4
B14: TOTALS | F14: =SUM(F7:F13) -> 1000 | G14: =SUM(G7:G13) -> 8377.8867 | H14: =SUM(H7:H13) -> 9377.8867 | J14: =SUM(J7:J13) -> 565.48673 | K14: =SUM(K7:K13) -> -434.51327 | L14: =SUM(L7:L13) -> 1.2
B16: SCORECARD
B17: Wins | C17: =COUNTIF(I7:I13,"Win") -> 1
B18: Losses | C18: =COUNTIF(I7:I13,"Loss") -> 6
B19: Pushes | C19: =COUNTIF(I7:I13,"Push") -> 0
B20: Pending | C20: =COUNTIF(I7:I13,"Pending") -> 0
B21: Hit Rate | C21: =IF(COUNTIF(I7:I13,"Win")+COUNTIF(I7:I13,"Loss")=0,"—",COUNTIF(I7:I13,"Win")/(COUNTIF(I7:I13,"Win")+COUNTIF(I7:I13,"Loss"))) -> 0.14285714
B22: Total Staked | C22: =SUM(F7:F13) -> 1000
B23: Total Returned | C23: =SUM(J7:J13) -> 565.48673
B24: Net P/L | C24: =SUM(K7:K13) -> -434.51327
B25: ROI | C25: =IF(SUM(F7:F13)=0,"—",SUM(K7:K13)/SUM(F7:F13)) -> -0.43451327
B26: Expected Wins (model) | C26: =SUM(L7:L13) -> 1.2
B27: Best-Case P/L (basket excl.) | C27: =2678 -> 2678
A29: Yellow = fill in results (dropdown). Blue = inputs. Black = formulas. 'Max Return' is intentionally omitted: bets 3-7 are mutually exclusive, so summing their returns would be meaningless.

Sheet References
A1: DATA SOURCES — WHERE THE FACTS COME FROM
A2: Root sites queried for research, odds, and results. New rows/columns appended as future tests use new sources. Discovery via web search; sites below are where facts were actually read.
A4: Root Site | B4: Type of Content Pulled | C4: T1 UFC | D4: T2 WC | E4: T3 MLB | F4: T4 NASCAR | G4: Notes
A5: espn.com | B5: Odds boards, live scores, schedules, brackets | D5: ✓ | E5: ✓ | G5: Primary MLB odds board; WC scores
A6: ufc.com | B6: Official UFC fight results | C6: ✓ | G6: Official source used to grade Test 1
A7: mmaweekly.com | B7: Full fight results incl. early prelims | C7: ✓ | G7: Prelim results for Test 1 grading
A8: vegasinsider.com | B8: Sportsbook odds aggregation (BetMGM) | D8: ✓ | G8: WC championship futures
A9: covers.com | B9: Odds, picks, prediction-market data | D9: ✓ | F9: ✓ | G9: WC: Kalshi probabilities (SEE CAUTION BELOW) · NASCAR: outrights, H2H, props · WNBA: Fever-Aces picks/props (T5)
A10: dknetwork.draftkings.com | B10: DraftKings opening lines & analysis | D10: ✓ | E10: ✓ | G10: WC semifinal openers; MLB parlay research
A11: sports.yahoo.com | B11: Brackets, schedules, lineups, reports | D11: ✓ | F11: ✓ | G11: WC bracket; NASCAR starting lineup/race info
A12: vavel.com | B12: Live match blogs | D12: ✓ | G12: Live Argentina-Switzerland score
A13: foxsports.com | B13: Odds stories, score pages | D13: ✓ | G13: WC title odds context
A14: nbcsports.com | B14: Match previews & broadcast info | D14: ✓ | G14: Argentina-Switzerland preview
A15: wikipedia.org | B15: Tournament format & structure | D15: ✓ | G15: WC knockout format/dates
A16: vsin.com | B16: Expert betting analysis & picks | E16: ✓ | F16: ✓ | G16: MLB Sunday card; NASCAR top-5 picks & longshots
A17: pickdawgz.com | B17: Game predictions with stats | E17: ✓ | G17: Brewers-Pirates deep dive
A18: mlb.com | B18: Official schedules & probable pitchers | E18: ✓ | G18: Probable-pitcher confirmation
A19: cbssports.com | B19: Model-based picks & odds (FanDuel) | F19: ✓ | G19: SportsLine model: Keselowski call, Blaney fade
A20: si.com | B20: Betting lines, picks & player props (FanDuel) | D20: ✓ | F20: ✓ | G20: T2: France-Spain lines · T5 WNBA: all game lines & props
A21: golfdigest.com | B21: Golf major picks & player analysis | G21: T6 Open: 13-best-bets breakdown, form/course fit
A22: sportsbettingdime.com | B22: Odds tracking (DraftKings) | G22: T6 Open: outright board · also WC SF openers
A23: all.rugby | B23: Rugby fixtures & results | G23: T7 Rugby: Nations Cup rounds 1-2 results, Rd 3 fixtures
A25: ⚠ SOURCE CAUTION — KALSHI (per John, 2026-07-12): prediction-market prices can be manipulated ('market rigging'). Kalshi probabilities are used for CONTEXT/comparison only, never as a primary betting basis. Primary basis = sportsbook consensus + our own stats analysis.
A26: Sportsbook prices quoted within these pages: DraftKings, BetMGM, FanDuel.
A27: Test 1 note: the original UFC 329 card (previous session) cited DraftKings / BetMGM / CBS Sports; graded from ufc.com + mmaweekly.com.
A28: Sites queried but returning no usable facts (blocked/empty) are not listed.
A29: Test 8 · HR Derby Jul 13 | B29: dknetwork.draftkings.com (outright odds); actionnetwork.com (format, props); vsin.com (props, picks); sports.yahoo.com (event info); mlb.com (schedule)
A30: Test 9 · WNBA Jul 15 | B30: covers.com (Fever-Valkyries odds); dratings.com (slate, projections); actionnetwork.com (Sparks-Lynx); fantasyalarm.com (Fever preview); espn.com (records)

Sheet WNBA Jul 12
A1: TEST 5 — WNBA SUNDAY NIGHT DOUBLEHEADER · JULY 12, 2026 | H1: STATUS: SETTLED — 3-4 (42.9%), -$298.15 · Fever routed Aces 109-75
A2: Sky @ Wings 7 PM ET (ESPN) · Fever @ Aces 9 PM ET (NBC) · Source: wnba-jul12-betting-card.html · Lines: FanDuel via SI Betting / Covers, ~5 PM CT
A3: Budget $1,000 · 6 core bets + 1 longshot (counts toward the account longshot record). EV ≈ +$81, expected wins ≈ 3.6 of 7.
A5: ACTIVE BETS
A6: # | B6: Pick | C6: Game / Market | D6: Bet Type | E6: Odds (Am.) | F6: Stake | G6: To Win | H6: Potential Return | I6: Result | J6: Returned | K6: P/L | L6: Est. Win % | M6: Notes
A7: 1 | B7: Wings -9.5 | C7: vs Sky · 7 PM ET | D7: Spread | E7: -115 | F7: 200 | G7: =IF(E7>0,F7*E7/100,F7*100/ABS(E7)) -> 173.91304 | H7: =F7+G7 -> 373.91304 | I7: Loss | J7: =IF(I7="Win",F7+G7,IF(I7="Push",F7,IF(I7="Loss",0,0))) -> 0 | K7: =IF(I7="Pending",0,J7-F7) -> -200 | L7: 0.56 | M7: Sky missing Carrington + Diggins; Wings 15-8, 2nd in O-rating last 10 · RESULT: DAL 82-79 — won by 3, spread dead
A8: 2 | B8: Sky @ Wings Over 177.5 | C8: Game 1 total | D8: Total | E8: -112 | F8: 150 | G8: =IF(E8>0,F8*E8/100,F8*100/ABS(E8)) -> 133.92857 | H8: =F8+G8 -> 283.92857 | I8: Loss | J8: =IF(I8="Win",F8+G8,IF(I8="Push",F8,IF(I8="Loss",0,0))) -> 0 | K8: =IF(I8="Pending",0,J8-F8) -> -150 | L8: 0.56 | M8: 185 & 188 combined in first two meetings; Sky 3rd in pace, over 8 of last 10 · RESULT: 161 combined — 16.5 under the number
A9: 3 | B9: Paige Bueckers 20+ Points | C9: Wings G · player prop | D9: Prop | E9: -159 | F9: 150 | G9: =IF(E9>0,F9*E9/100,F9*100/ABS(E9)) -> 94.339623 | H9: =F9+G9 -> 244.33962 | I9: Win | J9: =IF(I9="Win",F9+G9,IF(I9="Push",F9,IF(I9="Loss",0,0))) -> 244.33962 | K9: =IF(I9="Pending",0,J9-F9) -> 94.339623 | L9: 0.65 | M9: 22+ in 6 of last 7; 20.6 PPG; Sky 10th in D-rating · RESULT: Bueckers 20 pts (6-13 FG, 7-8 FT) — cleared at the buzzer of our line
A10: 4 | B10: Aces -4.5 | C10: vs Fever · 9 PM ET | D10: Spread | E10: -108 | F10: 150 | G10: =IF(E10>0,F10*E10/100,F10*100/ABS(E10)) -> 138.88889 | H10: =F10+G10 -> 288.88889 | I10: Loss | J10: =IF(I10="Win",F10+G10,IF(I10="Push",F10,IF(I10="Loss",0,0))) -> 0 | K10: =IF(I10="Pending",0,J10-F10) -> -150 | L10: 0.55 | M10: +41 differential last 7 home w/ Wilson; rested off 48-pt blowout Sat · RESULT: Fever 109-75 — Aces lost by 34, spread dead
A11: 5 | B11: A'ja Wilson Double-Double (Yes) | C11: Aces F · player prop | D11: Prop | E11: -120 | F11: 130 | G11: =IF(E11>0,F11*E11/100,F11*100/ABS(E11)) -> 108.33333 | H11: =F11+G11 -> 238.33333 | I11: Win | J11: =IF(I11="Win",F11+G11,IF(I11="Push",F11,IF(I11="Loss",0,0))) -> 238.33333 | K11: =IF(I11="Pending",0,J11-F11) -> 108.33333 | L11: 0.6 | M11: DD in 5 straight career games vs Clark; 10.8 reb/game at home; 11 DDs (3rd in W) · RESULT: Wilson 20 pts / 12 reb — double-double cashed
A12: 6 | B12: Kelsey Mitchell Over 2.5 Threes | C12: Fever G · player prop | D12: Prop | E12: -121 | F12: 120 | G12: =IF(E12>0,F12*E12/100,F12*100/ABS(E12)) -> 99.173554 | H12: =F12+G12 -> 219.17355 | I12: Win | J12: =IF(I12="Win",F12+G12,IF(I12="Push",F12,IF(I12="Loss",0,0))) -> 219.17355 | K12: =IF(I12="Pending",0,J12-F12) -> 99.173554 | L12: 0.58 | M12: 3+ threes in 6 straight, 8 of 10; 41.1% from deep; LV 12th vs opp threes · RESULT: Mitchell 3-of-8 from deep (27 pts) — cleared 2.5
A13: 7 | B13: LONGSHOT: 4-Leg Parlay | C13: Wings -9.5 / Aces -4.5 / Bueckers 20+ / Mitchell 3+ threes | D13: Parlay | E13: 971 | F13: 100 | G13: =IF(E13>0,F13*E13/100,F13*100/ABS(E13)) -> 971 | H13: =F13+G13 -> 1071 | I13: Loss | J13: =IF(I13="Win",F13+G13,IF(I13="Push",F13,IF(I13="Loss",0,0))) -> 0 | K13: =IF(I13="Pending",0,J13-F13) -> -100 | L13: 0.12 | M13: Stacks our four highest-confidence legs · counts in longshot record · RESULT: Wings -9.5 leg dead → parlay dead (longshot MISS)
B14: TOTALS | F14: =SUM(F7:F13) -> 1000 | G14: =SUM(G7:G13) -> 1719.577 | H14: =SUM(H7:H13) -> 2719.577 | J14: =SUM(J7:J13) -> 701.84651 | K14: =SUM(K7:K13) -> -298.15349 | L14: =SUM(L7:L13) -> 3.62
B16: SCORECARD
B17: Wins | C17: =COUNTIF(I7:I13,"Win") -> 3
B18: Losses | C18: =COUNTIF(I7:I13,"Loss") -> 4
B19: Pushes | C19: =COUNTIF(I7:I13,"Push") -> 0
B20: Pending | C20: =COUNTIF(I7:I13,"Pending") -> 0
B21: Hit Rate | C21: =IF(COUNTIF(I7:I13,"Win")+COUNTIF(I7:I13,"Loss")=0,"—",COUNTIF(I7:I13,"Win")/(COUNTIF(I7:I13,"Win")+COUNTIF(I7:I13,"Loss"))) -> 0.42857143
B22: Total Staked | C22: =SUM(F7:F13) -> 1000
B23: Total Returned | C23: =SUM(J7:J13) -> 701.84651
B24: Net P/L | C24: =SUM(K7:K13) -> -298.15349
B25: ROI | C25: =IF(SUM(F7:F13)=0,"—",SUM(K7:K13)/SUM(F7:F13)) -> -0.29815349
B26: Max Return (all hit) | C26: =SUM(H7:H13) -> 2719.577
B27: Expected Wins (model) | C27: =SUM(L7:L13) -> 3.62
B28: Expected Value (model) | C28: =SUMPRODUCT(L7:L13,G7:G13)-SUMPRODUCT(1-L7:L13,F7:F13) -> 84.741609
A30: Yellow = fill in results (dropdown). Blue = inputs. Black = formulas. Parlay odds +971 = (-115 × -108 × -159 × -121) compounded; grades as one bet.

Sheet The Open
A1: TEST 6 — THE 154th OPEN CHAMPIONSHIP · ROYAL BIRKDALE · JULY 16-19, 2026 | H1: STATUS: ACTIVE — R1 COMPLETE Thu Jul 16: Suber leads −5 (65); Morikawa −3 best on card · $1,000 fully deployed
A2: Source: open2026-betting-card.html · Outrights locked Sun Jul 12 · Phase 2 top-10 props deployed Wed Jul 15 (reserved $400 now at risk)
A3: Outright basket (rows 7-12) mutually exclusive — max one cashes. Phase 2 = 5 top-10 props (rows 13-17). Full $1,000 now deployed.
A5: ACTIVE BETS
A6: # | B6: Pick | C6: Market | D6: Bet Type | E6: Odds (Am.) | F6: Stake | G6: To Win | H6: Potential Return | I6: Result | J6: Returned | K6: P/L | L6: Est. Win % | M6: Notes
A7: 1 | B7: Scottie Scheffler | C7: Outright winner | D7: Outright | E7: 450 | F7: 200 | G7: =IF(E7>0,F7*E7/100,F7*100/ABS(E7)) -> 900 | H7: =F7+G7 -> 1100 | I7: Pending | J7: =IF(I7="Win",F7+G7,IF(I7="Push",F7,IF(I7="Loss",0,0))) -> 0 | K7: =IF(I7="Pending",0,J7-F7) -> 0 | L7: 0.18 | M7: Anchor — defending champ, drought discount on world No. 1
A8: 2 | B8: Jon Rahm | C8: Outright winner | D8: Outright | E8: 1600 | F8: 100 | G8: =IF(E8>0,F8*E8/100,F8*100/ABS(E8)) -> 1600 | H8: =F8+G8 -> 1700 | I8: Pending | J8: =IF(I8="Win",F8+G8,IF(I8="Push",F8,IF(I8="Loss",0,0))) -> 0 | K8: =IF(I8="Pending",0,J8-F8) -> 0 | L8: 0.07 | M8: Two majors, near-misses all season, wind player
A9: 3 | B9: Tommy Fleetwood | C9: Outright winner | D9: Outright | E9: 1600 | F9: 100 | G9: =IF(E9>0,F9*E9/100,F9*100/ABS(E9)) -> 1600 | H9: =F9+G9 -> 1700 | I9: Pending | J9: =IF(I9="Win",F9+G9,IF(I9="Push",F9,IF(I9="Loss",0,0))) -> 0 | K9: =IF(I9="Pending",0,J9-F9) -> 0 | L9: 0.07 | M9: Southport native — Birkdale is his home course
A10: 4 | B10: Matt Fitzpatrick | C10: Outright winner | D10: Outright | E10: 2000 | F10: 80 | G10: =IF(E10>0,F10*E10/100,F10*100/ABS(E10)) -> 1600 | H10: =F10+G10 -> 1680 | I10: Pending | J10: =IF(I10="Win",F10+G10,IF(I10="Push",F10,IF(I10="Loss",0,0))) -> 0 | K10: =IF(I10="Pending",0,J10-F10) -> 0 | L10: 0.055 | M10: 3 wins this season, English home major
A11: 5 | B11: Collin Morikawa | C11: Outright winner | D11: Outright | E11: 2800 | F11: 70 | G11: =IF(E11>0,F11*E11/100,F11*100/ABS(E11)) -> 1960 | H11: =F11+G11 -> 2030 | I11: Pending | J11: =IF(I11="Win",F11+G11,IF(I11="Push",F11,IF(I11="Loss",0,0))) -> 0 | K11: =IF(I11="Pending",0,J11-F11) -> 0 | L11: 0.045 | M11: 2021 Open champ, Sunday 61 at Travelers
A12: 6 | B12: Brooks Koepka (LONGSHOT) | C12: Outright winner | D12: Outright | E12: 5000 | F12: 50 | G12: =IF(E12>0,F12*E12/100,F12*100/ABS(E12)) -> 2500 | H12: =F12+G12 -> 2550 | I12: Pending | J12: =IF(I12="Win",F12+G12,IF(I12="Push",F12,IF(I12="Loss",0,0))) -> 0 | K12: =IF(I12="Pending",0,J12-F12) -> 0 | L12: 0.025 | M12: 5 majors, career-long price · counts in longshot record
A13: 7 | B13: Scottie Scheffler Top-10 | C13: Top-10 finish | D13: Prop | E13: -146 | F13: 120 | G13: =IF(E13>0,F13*E13/100,F13*100/ABS(E13)) -> 82.191781 | H13: =F13+G13 -> 202.19178 | I13: Pending | J13: =IF(I13="Win",F13+G13,IF(I13="Push",F13,IF(I13="Loss",0,0))) -> 0 | K13: =IF(I13="Pending",0,J13-F13) -> 0 | L13: 0.62 | M13: World #1 / +620 favorite; safest of the basket
A14: 8 | B14: Tommy Fleetwood Top-10 | C14: Top-10 finish | D14: Prop | E14: 158 | F14: 90 | G14: =IF(E14>0,F14*E14/100,F14*100/ABS(E14)) -> 142.2 | H14: =F14+G14 -> 232.2 | I14: Pending | J14: =IF(I14="Win",F14+G14,IF(I14="Push",F14,IF(I14="Loss",0,0))) -> 0 | K14: =IF(I14="Pending",0,J14-F14) -> 0 | L14: 0.44 | M14: Southport native, home links; strong value
A15: 9 | B15: Jon Rahm Top-10 | C15: Top-10 finish | D15: Prop | E15: 172 | F15: 80 | G15: =IF(E15>0,F15*E15/100,F15*100/ABS(E15)) -> 137.6 | H15: =F15+G15 -> 217.6 | I15: Pending | J15: =IF(I15="Win",F15+G15,IF(I15="Push",F15,IF(I15="Loss",0,0))) -> 0 | K15: =IF(I15="Pending",0,J15-F15) -> 0 | L15: 0.42 | M15: Elite wind player; value vs field
A16: 10 | B16: Matt Fitzpatrick Top-10 | C16: Top-10 finish | D16: Prop | E16: 164 | F16: 70 | G16: =IF(E16>0,F16*E16/100,F16*100/ABS(E16)) -> 114.8 | H16: =F16+G16 -> 184.8 | I16: Pending | J16: =IF(I16="Win",F16+G16,IF(I16="Push",F16,IF(I16="Loss",0,0))) -> 0 | K16: =IF(I16="Pending",0,J16-F16) -> 0 | L16: 0.42 | M16: English; 6 straight Open cuts made
A17: 11 | B17: Collin Morikawa Top-10 | C17: Top-10 finish | D17: Prop | E17: 280 | F17: 40 | G17: =IF(E17>0,F17*E17/100,F17*100/ABS(E17)) -> 112 | H17: =F17+G17 -> 152 | I17: Pending | J17: =IF(I17="Win",F17+G17,IF(I17="Push",F17,IF(I17="Loss",0,0))) -> 0 | K17: =IF(I17="Pending",0,J17-F17) -> 0 | L17: 0.3 | M17: 2021 Open champ, elite ballstriker
B18: TOTALS (deployed) | C18: =COUNTIF(I7:I12,"Loss") -> 0 | F18: =SUM(F7:F17) -> 1000 | G18: =SUM(G7:G17) -> 10748.792 | H18: =SUM(H7:H17) -> 11748.792 | J18: =SUM(J7:J17) -> 0 | K18: =SUM(K7:K17) -> 0 | L18: =SUM(L7:L17) -> 2.645
B19: Pending | C19: =COUNTIF(I7:I12,"Pending") -> 6
B20: Hit Rate | C20: =IF(COUNTIF(I7:I12,"Win")+COUNTIF(I7:I12,"Loss")=0,"—",COUNTIF(I7:I12,"Win")/(COUNTIF(I7:I12,"Win")+COUNTIF(I7:I12,"Loss"))) -> —
B21: Total Staked (Phase 1) | C21: =SUM(F7:F12) -> 600
B22: Total Returned | C22: =SUM(J7:J12) -> 0
B23: Net P/L | C23: =SUM(K7:K12) -> 0
B24: Basket Coverage (one wins) | C24: =SUM(L7:L12) -> 0.445

Sheet HR Derby
A1: TEST 8 — MLB HOME RUN DERBY · CITIZENS BANK PARK, PHILADELPHIA · JULY 13, 2026 | H1: STATUS: SETTLED Jul 13 — 2-5 · net -$475.00 · Walker stunned Schwarber 12-11 in the final
A2: 8 PM ET / 7 CT on Netflix · Source: cards/hrderby-jul13-betting-card.html · Outrights: DraftKings ~9 AM CT Jul 13 · Props: Action Network / VSiN lines, -110 std price
A3: Bets 1, 2, 7 mutually exclusive (one winner). New format: 20 swings R1, top 4 to bracket (1v4/2v3), 15-swing semis+final, bonus swings while homering.
A5: ACTIVE BETS
A6: # | B6: Pick | C6: Market | D6: Bet Type | E6: Odds (Am.) | F6: Stake | G6: To Win | H6: Potential Return | I6: Result | J6: Returned | K6: P/L | L6: Est. Win % | M6: Notes
A7: 1 | B7: Kyle Schwarber | C7: Outright winner | D7: Outright | E7: 310 | F7: 220 | G7: =IF(E7>0,F7*E7/100,F7*100/ABS(E7)) -> 682 | H7: =F7+G7 -> 902 | I7: Loss | J7: =IF(I7="Win",F7+G7,IF(I7="Push",F7,IF(I7="Loss",0,0))) -> 0 | K7: =IF(I7="Pending",0,J7-F7) -> -220 | L7: 0.27 | M7: Anchor — MLB HR leader (32), home park, format suits him — Runner-up: 11 HRs in final, Walker homered on his last 6 swings to win 12-11 (theScore + SI agree)
A8: 2 | B8: Junior Caminero | C8: Outright winner | D8: Outright | E8: 425 | F8: 130 | G8: =IF(E8>0,F8*E8/100,F8*100/ABS(E8)) -> 552.5 | H8: =F8+G8 -> 682.5 | I8: Loss | J8: =IF(I8="Win",F8+G8,IF(I8="Push",F8,IF(I8="Loss",0,0))) -> 0 | K8: =IF(I8="Pending",0,J8-F8) -> -130 | L8: 0.18 | M8: 44 HR in last year's derby, same BP pitcher — R1 12 HRs (3rd), semis: fell 6-5 to Walker (theScore + AP agree)
A9: 3 | B9: Schwarber R1 Over 10.5 HRs | C9: Round 1 total | D9: Prop | E9: -110 | F9: 180 | G9: =IF(E9>0,F9*E9/100,F9*100/ABS(E9)) -> 163.63636 | H9: =F9+G9 -> 343.63636 | I9: Loss | J9: =IF(I9="Win",F9+G9,IF(I9="Push",F9,IF(I9="Loss",0,0))) -> 0 | K9: =IF(I9="Pending",0,J9-F9) -> -180 | L9: 0.6 | M9: 20 swings + bonus rule; 11 clears — R1: Schwarber hit exactly 10, under by half a homer (theScore + AP agree)
A10: 4 | B10: Total Derby HRs Over 119.5 | C10: Event total | D10: Prop | E10: -110 | F10: 150 | G10: =IF(E10>0,F10*E10/100,F10*100/ABS(E10)) -> 136.36364 | H10: =F10+G10 -> 286.36364 | I10: Win | J10: =IF(I10="Win",F10+G10,IF(I10="Push",F10,IF(I10="Loss",0,0))) -> 286.36364 | K10: =IF(I10="Pending",0,J10-F10) -> 136.36364 | L10: 0.58 | M10: Bonus-swing rule + Philly July carry — Cleared easily: 80 in R1 + 27 in semis + 23 in final ≈ 130 total (multi-source tallies)
A11: 5 | B11: Ben Rice R1 Over 9.5 HRs | C11: Round 1 total | D11: Prop | E11: -110 | F11: 120 | G11: =IF(E11>0,F11*E11/100,F11*100/ABS(E11)) -> 109.09091 | H11: =F11+G11 -> 229.09091 | I11: Loss | J11: =IF(I11="Win",F11+G11,IF(I11="Push",F11,IF(I11="Loss",0,0))) -> 0 | K11: =IF(I11="Pending",0,J11-F11) -> -120 | L11: 0.57 | M11: Lefty pull power, 330-ft RF corner — VSiN lean — R1: Rice managed just 7 of 20, first man eliminated (theScore; AP confirms did not advance)
A12: 6 | B12: Longest HR Over 484.5 ft | C12: Distance prop | D12: Prop | E12: -110 | F12: 125 | G12: =IF(E12>0,F12*E12/100,F12*100/ABS(E12)) -> 113.63636 | H12: =F12+G12 -> 238.63636 | I12: Win | J12: =IF(I12="Win",F12+G12,IF(I12="Push",F12,IF(I12="Loss",0,0))) -> 238.63636 | K12: =IF(I12="Pending",0,J12-F12) -> 113.63636 | L12: 0.56 | M12: Contreras 490-ft R1 blast clears 484.5 — graded live mid-event (NESN/Sportsnet/Yahoo agree)
A13: 7 | B13: LONGSHOT: Willson Contreras | C13: Outright winner | D13: Outright | E13: 1400 | F13: 75 | G13: =IF(E13>0,F13*E13/100,F13*100/ABS(E13)) -> 1050 | H13: =F13+G13 -> 1125 | I13: Loss | J13: =IF(I13="Win",F13+G13,IF(I13="Push",F13,IF(I13="Loss",0,0))) -> 0 | K13: =IF(I13="Pending",0,J13-F13) -> -75 | L13: 0.07 | M13: Longest price on board · counts in longshot record — Stole the show: 13-HR R1 + 490-ft blast, booed by 45k, out 9-8 to Schwarber on his final semifinal swing (theScore + AP)
B14: TOTALS | F14: =SUM(F7:F13) -> 1000 | G14: =SUM(G7:G13) -> 2807.2273 | H14: =SUM(H7:H13) -> 3807.2273 | J14: =SUM(J7:J13) -> 525 | K14: =SUM(K7:K13) -> -475

Sheet WNBA Jul 15
A1: TEST 9 — WNBA WEDNESDAY SLATE · JULY 15, 2026 | H1: STATUS: SETTLED — 2-5 (28.6%), -$446.85 · Valkyries spoil the party; Clark restricted to 26 min
A2: Source: cards/wnba-jul15-betting-card.html · Lines: DraftKings/Caesars/consensus, locked ~9 PM CT Jul 14
A3: 3 games: Sparks@Lynx (~12 PM CT), Storm@Sky (aft), Fever vs Valkyries 7 PM CT. Clark prop = Over 22.5 points.
A5: ACTIVE BETS
A6: # | B6: Pick | C6: Market | D6: Bet Type | E6: Odds (Am.) | F6: Stake | G6: To Win | H6: Potential Return | I6: Result | J6: Returned | K6: P/L | L6: Est. Win % | M6: Notes
A7: 1 | B7: Fever -3.5 | C7: vs Valkyries · 7 PM CT | D7: Spread | E7: -105 | F7: 185 | G7: =IF(E7>0,F7*E7/100,F7*100/ABS(E7)) -> 176.19048 | H7: =F7+G7 -> 361.19048 | I7: Loss | J7: =IF(I7="Win",F7+G7,IF(I7="Push",F7,IF(I7="Loss",0,0))) -> 0 | K7: =IF(I7="Pending",0,J7-F7) -> -185 | L7: 0.57 | M7: Home, 7-game heater, Clark healthy; anchor · RESULT: Valkyries 88-75 — Fever lost outright by 13, spread dead
A8: 2 | B8: Fever–Valkyries Over 169.5 | C8: Headliner total | D8: Total | E8: -115 | F8: 175 | G8: =IF(E8>0,F8*E8/100,F8*100/ABS(E8)) -> 152.17391 | H8: =F8+G8 -> 327.17391 | I8: Loss | J8: =IF(I8="Win",F8+G8,IF(I8="Push",F8,IF(I8="Loss",0,0))) -> 0 | K8: =IF(I8="Pending",0,J8-F8) -> -175 | L8: 0.54 | M8: Two top-8 offenses, Clark pace, soft number · RESULT: 163 combined — 6.5 under the number
A9: 3 | B9: Sparks–Lynx Over 182.5 | C9: Afternoon total | D9: Total | E9: -110 | F9: 160 | G9: =IF(E9>0,F9*E9/100,F9*100/ABS(E9)) -> 145.45455 | H9: =F9+G9 -> 305.45455 | I9: Win | J9: =IF(I9="Win",F9+G9,IF(I9="Push",F9,IF(I9="Loss",0,0))) -> 305.45455 | K9: =IF(I9="Pending",0,J9-F9) -> 145.45455 | L9: 0.55 | M9: Lynx offense + Sparks poor D & fast pace · RESULT: Lynx 96-87 — 183 combined, over by half a point
A10: 4 | B10: Caitlin Clark Over 22.5 points | C10: Fever G · player prop | D10: Prop | E10: -110 | F10: 150 | G10: =IF(E10>0,F10*E10/100,F10*100/ABS(E10)) -> 136.36364 | H10: =F10+G10 -> 286.36364 | I10: Loss | J10: =IF(I10="Win",F10+G10,IF(I10="Push",F10,IF(I10="Loss",0,0))) -> 0 | K10: =IF(I10="Pending",0,J10-F10) -> -150 | L10: 0.54 | M10: Home usage vs beatable Valkyries D; Clark healthy, no minutes cap · RESULT: Clark 13 pts (4-14 FG, 1-8 3PT) in 26 min on minutes restriction — well under 22.5
A11: 5 | B11: Chicago Sky ML | C11: vs Storm · afternoon | D11: Moneyline | E11: -130 | F11: 140 | G11: =IF(E11>0,F11*E11/100,F11*100/ABS(E11)) -> 107.69231 | H11: =F11+G11 -> 247.69231 | I11: Win | J11: =IF(I11="Win",F11+G11,IF(I11="Push",F11,IF(I11="Loss",0,0))) -> 247.69231 | K11: =IF(I11="Pending",0,J11-F11) -> 107.69231 | L11: 0.58 | M11: vs 6-19 Storm, home side of bad-vs-bad · RESULT: Sky 95-90 over Storm — ML cashed
A12: 6 | B12: Lynx -12.5 | C12: vs Sparks · afternoon | D12: Spread | E12: -110 | F12: 115 | G12: =IF(E12>0,F12*E12/100,F12*100/ABS(E12)) -> 104.54545 | H12: =F12+G12 -> 219.54545 | I12: Loss | J12: =IF(I12="Win",F12+G12,IF(I12="Push",F12,IF(I12="Loss",0,0))) -> 0 | K12: =IF(I12="Pending",0,J12-F12) -> -115 | L12: 0.52 | M12: 18-6 vs 10-12; sized down, back-door risk · RESULT: Lynx won by 9 — needed 13, spread dead
A13: 7 | B13: LONGSHOT: 4-Leg Parlay | C13: Fever -3.5 / Lynx O182.5 / Fever O169.5 / Sky ML | D13: Parlay | E13: 1133 | F13: 75 | G13: =IF(E13>0,F13*E13/100,F13*100/ABS(E13)) -> 849.75 | H13: =F13+G13 -> 924.75 | I13: Loss | J13: =IF(I13="Win",F13+G13,IF(I13="Push",F13,IF(I13="Loss",0,0))) -> 0 | K13: =IF(I13="Pending",0,J13-F13) -> -75 | L13: 0.1 | M13: Cross-game stack; counts in longshot record · RESULT: Fever -3.5 leg dead at the first hurdle → parlay dead (longshot MISS, 0-for-6)
B14: TOTALS | F14: =SUM(F7:F13) -> 1000 | G14: =SUM(G7:G13) -> 1672.1703 | H14: =SUM(H7:H13) -> 2672.1703 | J14: =SUM(J7:J13) -> 553.14685 | K14: =SUM(K7:K13) -> -446.85315
